MANIFEST.in
README.rst
setup.py
django_postmark.egg-info/PKG-INFO
django_postmark.egg-info/SOURCES.txt
django_postmark.egg-info/dependency_links.txt
django_postmark.egg-info/requires.txt
django_postmark.egg-info/top_level.txt
postmark/__init__.py
postmark/admin.py
postmark/backends.py
postmark/models.py
postmark/signals.py
postmark/urls.py
postmark/views.py
postmark/migrations/0001_initial.py
postmark/migrations/0002_auto__chg_field_emailmessage_tag.py
postmark/migrations/__init__.py