Metadata-Version: 1.0
Name: django-postmark
Version: 0.1.6
Summary: A Django reusable app to send email with postmark, as well as models and views to handle bounce integration.
Home-page: http://github.com/dstufft/django-postmark/
Author: Donald Stufft
Author-email: donald@e.vilgeni.us
License: BSD
Platform: UNKNOWN
Classifier: Development Status :: 4 - Beta
Classifier: Environment :: Web Environment
Classifier: Intended Audience :: Developers
Classifier: License :: OSI Approved :: BSD License
Classifier: Operating System :: OS Independent
Classifier: Programming Language :: Python
Classifier: Topic :: Utilities
Classifier: Framework :: Django
